LICENSE
MANIFEST.in
README.rst
setup.cfg
setup.py
daemontools/AppInstance.py
daemontools/__init__.py
daemontools/daemonize.py
daemontools.egg-info/PKG-INFO
daemontools.egg-info/SOURCES.txt
daemontools.egg-info/dependency_links.txt
daemontools.egg-info/top_level.txt
daemontools.egg-info/zip-safe