Metadata-Version: 1.2
Name: daemontools
Version: 0.0.2a5
Summary: Daemonizing and single instance tools.
Home-page: https://github.com/medovarsky/daemon-tools
Author: Lubos Medovarsky
Author-email: lubos@medovarsky.com
License: UNKNOWN
Keywords: daemon,single,instance,daemontools
Platform: UNKNOWN
Classifier: Development Status :: 3 - Alpha
Classifier: Environment :: No Input/Output (Daemon)
Classifier: Intended Audience :: Developers
Classifier: License :: OSI Approved :: GNU Lesser General Public License v3 or later (LGPLv3+)
Classifier: Operating System :: POSIX :: Linux
Classifier: Programming Language :: Python :: 3.6
Requires-Python: >=2.6
